data_transform_spark/__init__.py
data_transform_spark/data_transformer.py
data_transform_spark/mediator/__init__.py
data_transform_spark/mediator/abstract_dataset_mediator.py
data_transform_spark/mediator/dataset_logger.py
aissemble_extensions_transform_spark_python-2.0.0.dist-info/LICENSE
aissemble_extensions_transform_spark_python-2.0.0.dist-info/METADATA
aissemble_extensions_transform_spark_python-2.0.0.dist-info/WHEEL
aissemble_extensions_transform_spark_python-2.0.0.dist-info/RECORD
