Metadata-Version: 2.3
Name: aissemble-extensions-transform-spark-python
Version: 2.0.0
Summary: Contains the core Python implementation of data transform for Spark
License: Apache-2.0
Author: aiSSEMBLE Baseline Community
Author-email: aissemble@bah.com
Requires-Python: >=3.9
Classifier: License :: OSI Approved :: Apache Software License
Classifier: Programming Language :: Python :: 3
Classifier: Programming Language :: Python :: 3.9
Classifier: Programming Language :: Python :: 3.10
Classifier: Programming Language :: Python :: 3.11
Classifier: Programming Language :: Python :: 3.12
Classifier: Programming Language :: Python :: 3.13
Requires-Dist: aissemble-foundation-core-python (==2.0.0)
Requires-Dist: aissemble-foundation-transform-core-python (==2.0.0)
Requires-Dist: cryptography (>=42.0.4)
Requires-Dist: krausening (>=21)
Requires-Dist: pydantic (>=2.8.0)
Requires-Dist: pyspark (==3.5.5)
Requires-Dist: urllib3 (>=2.5.0,<3.0.0)
Project-URL: Documentation, https://boozallen.github.io/aissemble
Project-URL: Homepage, https://github.com/boozallen/aissemble
Project-URL: Repository, https://github.com/boozallen/aissemble
